PBundler
