Metadata-Version: 1.1
Name: pbundler
Version: 0.0.4
Summary: Bundler for Python
Home-page: http://github.com/zeha/pbundler/
Author: Christian Hofstaedtler
Author-email: ch--pypi@zeha.at
License: MIT
Download-URL: https://github.com/zeha/pbundler/downloads
Keywords: bundler bundle pbundler pbundle dependency dependencies management virtualenv pip packages
Platform: UNKNOWN
